pmlb/__init__.py
pmlb/_version.py
pmlb/all_summary_stats.tsv
pmlb/dataset_lists.py
pmlb/pmlb.py
pmlb/profiling.py
pmlb/update_dataset_files.py
pmlb-1.0.1.post3.dist-info/LICENSE
pmlb-1.0.1.post3.dist-info/METADATA
pmlb-1.0.1.post3.dist-info/WHEEL
pmlb-1.0.1.post3.dist-info/top_level.txt
pmlb-1.0.1.post3.dist-info/zip-safe
pmlb-1.0.1.post3.dist-info/RECORD
