Metadata-Version: 2.1
Name: pmlb
Version: 1.0.1.post3
Summary: A Python wrapper for the Penn Machine Learning Benchmark data repository.
Home-page: https://github.com/EpistasisLab/penn-ml-benchmarks
Author: Randal S. Olson, William La Cava, Trang Le, Weixuan Fu
Author-email: rso@randalolson.com, lacava@upenn.edu, ttle@pennmedicine.upenn.edu, weixuanf@pennmedicine.upenn.edu
License: License :: OSI Approved :: MIT License
Keywords: data mining,benchmark,machine learning,data analysis,data sets,data science,wrapper
Platform: UNKNOWN
Classifier: Intended Audience :: Developers
Classifier: Intended Audience :: Information Technology
Classifier: Intended Audience :: Science/Research
Classifier: License :: OSI Approved :: MIT License
Classifier: Programming Language :: Python :: 3.4
Classifier: Programming Language :: Python :: 3.5
Classifier: Programming Language :: Python :: 3.6
Classifier: Programming Language :: Python :: 3.7
Classifier: Topic :: Utilities
Provides-Extra: dev
